README.rst
setup.py
pycloser/__init__.py
pycloser/closer.py
pycloser.egg-info/PKG-INFO
pycloser.egg-info/SOURCES.txt
pycloser.egg-info/dependency_links.txt
pycloser.egg-info/top_level.txt