Metadata-Version: 1.0
Name: pycloser
Version: 0.2
Summary: Сlean exit for Python scripts after Ctrl-C.
Home-page: https://github.com/arvinkulagin/pycloser
Author: Arvin Kulagin
Author-email: arvinkulagin@yandex.ru
License: MIT
Keywords: signals exit
Platform: UNKNOWN
